study_gen/__init__.py
study_gen/__main__.py
study_gen/_nested_dicts.py
study_gen/block.py
study_gen/merge/__init__.py
study_gen/merge/_merge_blocks.py
study_gen/merge/merge.py
study_gen/study_gen.py
study_gen/templates/default.txt
study_gen/templates/with_context.txt
study_gen-0.4.2.dist-info/METADATA
study_gen-0.4.2.dist-info/WHEEL
study_gen-0.4.2.dist-info/RECORD
