Metadata-Version: 2.1
Name: study-gen
Version: 0.4.2
Summary: A tool to programmatically generate parametric studies.
Author: Colas Droin
Author-email: colasdroin@gmail.com
Requires-Python: >=3.11,<4.0
Classifier: Programming Language :: Python :: 3
Classifier: Programming Language :: Python :: 3.11
Classifier: Programming Language :: Python :: 3.12
Requires-Dist: argparse (>=1.4.0,<2.0.0)
Requires-Dist: black (>=24.1.1,<25.0.0)
Requires-Dist: ipykernel (>=6.28.0,<7.0.0)
Requires-Dist: jinja2 (>=3.1.3,<4.0.0)
Requires-Dist: matplotlib (>=3.8.2,<4.0.0)
Requires-Dist: numpy (>=1.26.2,<2.0.0)
Requires-Dist: pandas (>=2.1.3,<3.0.0)
Requires-Dist: ruamel-yaml (>=0.18.5,<0.19.0)
Requires-Dist: xmask (>=0.3.6,<0.4.0)
